uvpool/__init__.py
uvpool/web/__init__.py
uvpool/web/app.py
uvpool/web/global_settings.py
uvpool/web/handlers/__init__.py
uvpool/web/handlers/exception.py
uvpool/web/handlers/rollbar.py
uvpool/web/handlers/sentry.py
uvpool/web/info.py
uvpool/web/logging/__init__.py
uvpool/web/logging/protocol.py
uvpool/web/middleware/__init__.py
uvpool/web/middleware/request_id.py
uvpool/web/server.py
uvpool/web/views/__init__.py
uvpool/web/views/health.py
uvpool/web/worker.py
uvpool_web-0.2.0.dist-info/WHEEL
uvpool_web-0.2.0.dist-info/METADATA
uvpool_web-0.2.0.dist-info/RECORD
